jwt_token_parser_test_1/__init__.py
jwt_token_parser_test_1/token_parser.py
jwt_token_parser_test_1-0.1.0.dist-info/METADATA
jwt_token_parser_test_1-0.1.0.dist-info/WHEEL
jwt_token_parser_test_1-0.1.0.dist-info/top_level.txt
jwt_token_parser_test_1-0.1.0.dist-info/RECORD
