Metadata-Version: 2.1
Name: jwt-token-parser-test-1
Version: 0.1.0
Summary: Demo library
Home-page: https://jwt-token-parser-test-1.readthedocs.io/
Author: Malika Satimbaeva
Author-email: malikasatimbay@gmail.com
License: UNKNOWN
Platform: UNKNOWN
Classifier: Intended Audience :: Developers
Classifier: License :: OSI Approved :: MIT License
Classifier: Programming Language :: Python
Classifier: Programming Language :: Python :: 3
Classifier: Programming Language :: Python :: 3.6
Classifier: Programming Language :: Python :: 3.7
Classifier: Programming Language :: Python :: 3.8
Classifier: Programming Language :: Python :: 3.9
Classifier: Operating System :: OS Independent
Requires-Dist: python-jose
Requires-Dist: fastapi
Requires-Dist: pydantic
